multimm-1.1.5.dist-info/licenses/LICENSE
simulation/__init__.py
simulation/args_definition.py
simulation/initial_structure_tools.py
simulation/model.py
simulation/nucleosome_interpolation.py
simulation/plots.py
simulation/run.py
simulation/utils.py
simulation/validation.py
simulation/data/hg38_gtf_annotations.tsv
simulation/forcefields/dna_histones_ff.xml
simulation/forcefields/ff.xml
multimm-1.1.5.dist-info/METADATA
multimm-1.1.5.dist-info/WHEEL
multimm-1.1.5.dist-info/entry_points.txt
multimm-1.1.5.dist-info/top_level.txt
multimm-1.1.5.dist-info/RECORD
